ivcap_sdk_service/__init__.py
ivcap_sdk_service/aspect.py
ivcap_sdk_service/cio/__init__.py
ivcap_sdk_service/cio/cache.py
ivcap_sdk_service/cio/io_adapter.py
ivcap_sdk_service/cio/ivcap_io_adapter.py
ivcap_sdk_service/cio/local_io_adapter.py
ivcap_sdk_service/cio/readable_file.py
ivcap_sdk_service/cio/readable_proxy.py
ivcap_sdk_service/cio/utils.py
ivcap_sdk_service/cio/writable_file.py
ivcap_sdk_service/cio/writable_proxy.py
ivcap_sdk_service/config.py
ivcap_sdk_service/itypes.py
ivcap_sdk_service/ivcap.py
ivcap_sdk_service/logger.py
ivcap_sdk_service/run.py
ivcap_sdk_service/savers.py
ivcap_sdk_service/service.py
ivcap_sdk_service/utils.py
ivcap_sdk_service/verifiers.py
ivcap_sdk_service-0.8.0.dist-info/AUTHORS.md
ivcap_sdk_service-0.8.0.dist-info/LICENSE
ivcap_sdk_service-0.8.0.dist-info/METADATA
ivcap_sdk_service-0.8.0.dist-info/WHEEL
ivcap_sdk_service-0.8.0.dist-info/entry_points.txt
ivcap_sdk_service-0.8.0.dist-info/RECORD
