Metadata-Version: 2.1
Name: ivcap_sdk_service
Version: 0.8.0
Summary: SDK library for building services for the IVCAP platform
License: Proprietary
Author: Max Ott
Author-email: max.ott@csiro.au
Requires-Python: >=3.9,<4.0
Classifier: License :: Other/Proprietary License
Classifier: Programming Language :: Python :: 3
Classifier: Programming Language :: Python :: 3.9
Classifier: Programming Language :: Python :: 3.10
Classifier: Programming Language :: Python :: 3.11
Classifier: Programming Language :: Python :: 3.12
Requires-Dist: dataclass-wizard (>=0.22.0,<0.23.0)
Requires-Dist: filelock (>=3.13.1,<4.0.0)
Requires-Dist: filetype (>=1.2.0,<2.0.0)
Requires-Dist: importlib-metadata (>=7.1.0,<8.0.0)
Requires-Dist: jsonpath-ng (>=1.6.1,<2.0.0)
Requires-Dist: pydantic (>=2.6.1,<3.0.0)
Requires-Dist: pyyaml (>=6.0,<7.0)
Requires-Dist: requests (>=2.31,<3.0)
Requires-Dist: typing-extensions (>=4.9.0,<5.0.0)
Requires-Dist: validators (>=0.28.0)
Requires-Dist: watchdog (>=3.0.0)
